README.md
setup.py
maid_manga_id/__init__.py
maid_manga_id/http.py
maid_manga_id/maid_client.py
maid_manga_id/object.py
maid_manga_id/scaffold.py
maid_manga_id/utils.py
maid_manga_id.egg-info/PKG-INFO
maid_manga_id.egg-info/SOURCES.txt
maid_manga_id.egg-info/dependency_links.txt
maid_manga_id.egg-info/not-zip-safe
maid_manga_id.egg-info/requires.txt
maid_manga_id.egg-info/top_level.txt
maid_manga_id/methods/__init__.py
maid_manga_id/methods/manga/__init__.py
maid_manga_id/methods/manga/info.py
maid_manga_id/methods/manga/search.py
maid_manga_id/types/__init__.py
maid_manga_id/types/chapter.py
maid_manga_id/types/manga.py