Metadata-Version: 2.1
Name: maid-manga-id
Version: 1.1
Summary: Maid Manga Indonesia wrapper using Python BeautifulSoup.
Home-page: https://github.com/rushkii/maid_manga_id
Author: Kee
Author-email: riskimuhammmad1@gmail.com
License: MIT
Keywords: manga maid_manga maid_manga_id manga_id MaidMangaID
Platform: UNKNOWN
Classifier: Programming Language :: Python :: 3
Classifier: License :: OSI Approved :: MIT License
Classifier: Operating System :: OS Independent
